{"channelData": {
    "categoryTitle" : "Bzovík",
    "entries" : [
        {
        	"title" : "Peter Ostrihoň",
        	"url_title" : "peter-ostrihon",
        	"channel_name" : "kandidati",
        	"channel_title" : "Kandidáti",
        	"cislo" : "",
       		"summary" : "kandidát Kotleba ĽS NS na poslanca",
        	"fulltext" : "<p><b>Pre\u010do ste sa rozhodli kandidova\u0165 za poslanca?<\/b><\/p>\n\n<p>Chcem nie\u010do in\u00e9 urobi\u0165 pre \u013eud\u00ed, nielen im d\u00e1va\u0165 pr\u00e1zdne s\u013euby. Hanb\u00edm sa za starostu a poslancov, ktor\u00ed boli posledn\u00e9 roky, niektor\u00ed s\u00fa tam z nich u\u017e aj viac rokov, ako zanedb\u00e1vaj\u00fa dedinu a okolie. Konkr\u00e9tnej\u0161ie sa budem vyjadrova\u0165 a\u017e potom, ak sa stanem poslancom. <\/p>\n\n<p><b><br>\n<\/b><\/p>\n\n<p><b>V akej oblasti, \u010di pri rie\u0161en\u00ed ak\u00fdch probl\u00e9mov, sa najlep\u0161ie vyzn\u00e1te a m\u00f4\u017eete by\u0165 ob\u010danom n\u00e1pomocn\u00fd?<\/b><\/p>\n\n<p>V\u0161eobecne vo v\u0161etk\u00fdch oblastiach, v ktor\u00fdch by bolo potrebn\u00e9. <\/p>\n\n<p><b><br>\n<\/b><\/p>\n\n<p><b>Ktor\u00e9 3 konkr\u00e9tne veci chcete urobi\u0165 pre obec Bzov\u00edk a jej ob\u010danov?<\/b><\/p>\n\n<p>1. \u010disti\u010dka odpadov\u00fdch v\u00f4d<\/p>\n\n<p>2. chodn\u00edky<\/p>\n\n<p> <\/p>\n\n<p>3. \u0161portov\u00e9 akcie pre deti a akcie pre d\u00f4chodcov<\/p>",
        	"kandidati" : 0,  
        	"poslanci" : 0,  
        	"images" : null,  
        	"odpovede" : null, 
        	"otazky" : null
        
        }
    ]
  }
}